README.rst
setup.py
sydres/__init__.py
sydres.egg-info/PKG-INFO
sydres.egg-info/SOURCES.txt
sydres.egg-info/dependency_links.txt
sydres.egg-info/requires.txt
sydres.egg-info/top_level.txt