Metadata-Version: 1.1
Name: sydres
Version: 0.2.1
Summary: A client to submit payment orders to the Redsys service.
Home-page: https://github.com/alexbarcelo/sydres
Author: Alex Barcelo
Author-email: alex.barcelo@gmail.com
License: General Public Licence 3
Keywords: redsys,sydres
Platform: UNKNOWN
Classifier: Development Status :: 4 - Beta
Classifier: Programming Language :: Python
Classifier: Programming Language :: Python :: 3
Classifier: Topic :: Software Development :: Libraries :: Python Modules
Classifier: Topic :: Internet :: WWW/HTTP
Classifier: Operating System :: OS Independent
Classifier: Intended Audience :: Developers
Classifier: License :: OSI Approved :: GNU General Public License v3 (GPLv3)
Classifier: Environment :: Web Environment
Provides: sydres
